{
	"width": 512,
	"height": 512,
	"terrain": {
		"base_noise_scale": 0.8,
		"plates_counts": [7, 8],
		"plates_growth_probs_ranges": [[0.95, 1], [0.75, 0.825]],
		"continental_density": 2.7,
		"oceanic_density": 3.0,
		"features": {
			"mountain_range": {
			"width_min": 200,
			"width_max": 400
			},
			"volcanic_arc": {
				"width_min": 50,
				"width_max": 150,
				"offset_min": 100,
				"offset_max": 300
			},
			"trench": {
				"width_min": 50,
				"width_max": 100
			},
			"rift": {
				"width_min": 50,
				"width_max": 300	
			},
			"ocean_ridge": {
				"width_min": 10,
				"width_max": 60
			}
		},
		"blur_strengths": {
			"mountain": 2,
			"trench": 3,
			"volcanic_arc": 1
		}
	},
	"temperature": {
		"lapse_rate_c_per_km": 6.5,
		"equator_temp": 30,
		"pole_temp": -20,
		"noise_strength": 1.2
	},
	"precipitation": {
		"release_factor": 0.4,
		"retention_factor": 0.6,
		"moisture_initial_ocean": 1.0,
		"saturation_temp_factor": 0.05,
		"saturation_elev_factor": 0.01,
		"wind_strength": 1.0,
		"average_kernel_size": 3
	},
	"biome": {
		"sea_level_percent": 0.4,
        "colors": {
            "rock": [160, 160, 160],
            "highlands": [199, 196, 187],
            "ice sheet and polar desert": [225, 245, 255],
            "tundra": [188, 218, 230],
            "alpine tundra": [175, 210, 220],
            "taiga": [120, 160, 120],
            "temperate broadleaf forest": [75, 135, 60],
            "temperate steppe and savanna": [200, 170, 90],
            "subtropical evergreen forest": [60, 120, 95],
            "mediterranean": [178, 158, 87],
            "monsoon forests and mosaic": [50, 145, 85],
            
            "arid desert": [250, 215, 150],               
            "xeric shrubland": [240, 185, 140],          
            "dry steppe and thorn forest": [215, 175, 115],
            "semiarid desert": [240, 225, 185],           
            
            "grass savanna": [165, 205, 100],
            "tree savanna": [110, 170, 80],
            "dry forest and woodland savanna": [90, 145, 65],
            "tropical rainforest": [20, 110, 40],
            "montane forests and grasslands": [105, 125, 112],
            "deep water": [0, 0, 70],
            "shallow water": [0, 115, 160],
            "beach": [240, 220, 180]
        }
	}
}